.gitignore
LICENSE
MANIFEST.in
README.rst
setup.py
staticmedia handling.rst
django_staticmediamgr.egg-info/PKG-INFO
django_staticmediamgr.egg-info/SOURCES.txt
django_staticmediamgr.egg-info/dependency_links.txt
django_staticmediamgr.egg-info/top_level.txt
docs/.buildinfo
docs/app_media.html
docs/css_compression.html
docs/genindex.html
docs/getting_started.html
docs/index.html
docs/js_compression.html
docs/management_commands.html
docs/modindex.html
docs/objects.inv
docs/search.html
docs/searchindex.js
docs/segregatingmedia.html
docs/settings.html
docs/_sources/app_media.txt
docs/_sources/css_compression.txt
docs/_sources/getting_started.txt
docs/_sources/index.txt
docs/_sources/js_compression.txt
docs/_sources/management_commands.txt
docs/_sources/segregatingmedia.txt
docs/_sources/settings.txt
docs/_sources/reference/utils.txt
docs/_static/basic.css
docs/_static/breadcrumb_background.png
docs/_static/default.css
docs/_static/doctools.js
docs/_static/documentation.png
docs/_static/file.png
docs/_static/header_sm_mid.png
docs/_static/jquery.js
docs/_static/minus.png
docs/_static/plus.png
docs/_static/pygments.css
docs/_static/scrn1.png
docs/_static/scrn2.png
docs/_static/searchfield_leftcap.png
docs/_static/searchfield_repeat.png
docs/_static/searchfield_rightcap.png
docs/_static/searchtools.js
docs/_static/title_background.png
docs/_static/toc.js
docs/_static/triangle_closed.png
docs/_static/triangle_left.png
docs/_static/triangle_open.png
docs/reference/utils.html
docs_src/Makefile
docs_src/app_media.rst
docs_src/conf.py
docs_src/css_compression.rst
docs_src/getting_started.rst
docs_src/index.rst
docs_src/js_compression.rst
docs_src/make.bat
docs_src/management_commands.rst
docs_src/segregatingmedia.rst
docs_src/settings.rst
docs_src/_static/breadcrumb_background.png
docs_src/_static/default.css
docs_src/_static/documentation.png
docs_src/_static/header_sm_mid.png
docs_src/_static/scrn1.png
docs_src/_static/scrn2.png
docs_src/_static/searchfield_leftcap.png
docs_src/_static/searchfield_repeat.png
docs_src/_static/searchfield_rightcap.png
docs_src/_static/title_background.png
docs_src/_static/toc.js
docs_src/_static/triangle_closed.png
