Metadata-Version: 1.0
Name: django-staticmediamgr
Version: 0.6
Summary: A Django app to copy static media files over to a remote place, optionally minifying css and js.
Home-page: http://opensource.washingtontimes.com/projects/django-staticmediamgr/
Author: Corey Oordt, The Washington Times
Author-email: coordt@washingtontimes.com
License: UNKNOWN
Platform: UNKNOWN
Classifier: Development Status :: 4 - Beta
Classifier: Framework :: Django
Classifier: Intended Audience :: Developers
Classifier: License :: OSI Approved :: Apache Software License
